LICENSE
bigearthnet_patch_interface/__init__.py
bigearthnet_patch_interface/band_interface.py
bigearthnet_patch_interface/merged_interface.py
bigearthnet_patch_interface/patch_interface.py
bigearthnet_patch_interface/s1_interface.py
bigearthnet_patch_interface/s2_interface.py
bigearthnet_patch_interface/tiny_s2/S2A_MSIL2A_20170617T113321_36_85/S2A_MSIL2A_20170617T113321_36_85_B01.tif
bigearthnet_patch_interface/tiny_s2/S2A_MSIL2A_20170617T113321_36_85/S2A_MSIL2A_20170617T113321_36_85_B02.tif
bigearthnet_patch_interface/tiny_s2/S2A_MSIL2A_20170617T113321_36_85/S2A_MSIL2A_20170617T113321_36_85_B03.tif
bigearthnet_patch_interface/tiny_s2/S2A_MSIL2A_20170617T113321_36_85/S2A_MSIL2A_20170617T113321_36_85_B04.tif
bigearthnet_patch_interface/tiny_s2/S2A_MSIL2A_20170617T113321_36_85/S2A_MSIL2A_20170617T113321_36_85_B05.tif
bigearthnet_patch_interface/tiny_s2/S2A_MSIL2A_20170617T113321_36_85/S2A_MSIL2A_20170617T113321_36_85_B06.tif
bigearthnet_patch_interface/tiny_s2/S2A_MSIL2A_20170617T113321_36_85/S2A_MSIL2A_20170617T113321_36_85_B07.tif
bigearthnet_patch_interface/tiny_s2/S2A_MSIL2A_20170617T113321_36_85/S2A_MSIL2A_20170617T113321_36_85_B08.tif
bigearthnet_patch_interface/tiny_s2/S2A_MSIL2A_20170617T113321_36_85/S2A_MSIL2A_20170617T113321_36_85_B09.tif
bigearthnet_patch_interface/tiny_s2/S2A_MSIL2A_20170617T113321_36_85/S2A_MSIL2A_20170617T113321_36_85_B11.tif
bigearthnet_patch_interface/tiny_s2/S2A_MSIL2A_20170617T113321_36_85/S2A_MSIL2A_20170617T113321_36_85_B12.tif
bigearthnet_patch_interface/tiny_s2/S2A_MSIL2A_20170617T113321_36_85/S2A_MSIL2A_20170617T113321_36_85_B8A.tif
bigearthnet_patch_interface/tiny_s2/S2A_MSIL2A_20170617T113321_36_85/S2A_MSIL2A_20170617T113321_36_85_labels_metadata.json
bigearthnet_patch_interface-0.1.2.dist-info/WHEEL
bigearthnet_patch_interface-0.1.2.dist-info/METADATA
bigearthnet_patch_interface-0.1.2.dist-info/license_files/LICENSE
bigearthnet_patch_interface-0.1.2.dist-info/RECORD
