Metadata-Version: 2.1
Name: bigearthnet-patch-interface
Version: 0.1.2
Summary: A simple interface class that includes all the relevant information about BigEarthNet patches.
License: Apache Software License 2.0
Author-email: Kai Norman Clasen <k.clasen@protonmail.com>
Requires-Python: >=3.8
Requires-Dist: natsort>=8
Requires-Dist: numpy>=1.20
Requires-Dist: pydantic>=1.8
Project-URL: documentation, https://kai-tub.github.io/bigearthnet_patch_interface
Project-URL: homepage, https://github.com/kai-tub/bigearthnet_patch_interface/
Project-URL: repository, https://github.com/kai-tub/bigearthnet_patch_interface/
